spss_converter/Metadata.py
spss_converter/__init__.py
spss_converter/__version__.py
spss_converter/errors.py
spss_converter/read.py
spss_converter/write.py
spss_converter-0.2.0.dist-info/LICENSE
spss_converter-0.2.0.dist-info/METADATA
spss_converter-0.2.0.dist-info/WHEEL
spss_converter-0.2.0.dist-info/top_level.txt
spss_converter-0.2.0.dist-info/RECORD
